mcp_server_deepresearch/__init__.py
mcp_server_deepresearch/__main__.py
mcp_server_deepresearch/mcp_server.py
mcp_minideepsearch-0.1.0.dist-info/METADATA
mcp_minideepsearch-0.1.0.dist-info/WHEEL
mcp_minideepsearch-0.1.0.dist-info/entry_points.txt
mcp_minideepsearch-0.1.0.dist-info/top_level.txt
mcp_minideepsearch-0.1.0.dist-info/RECORD
