Metadata-Version: 2.4
Name: mcp-minideepsearch
Version: 0.1.0
Summary: A deep research agent based on LangGraph and MCP
Author-email: junfeizhu <jzhu60@163.com>
Requires-Python: >=3.10
Requires-Dist: langgraph>=0.2.0
Requires-Dist: langchain>=0.3.0
Requires-Dist: langchain-openai>=0.2.0
Requires-Dist: langchain-deepseek>=0.1.0
Requires-Dist: langchain-tavily>=0.1.0
Requires-Dist: langchain-core>=0.3.0
Requires-Dist: langchain-community>=0.3.0
Requires-Dist: python-dotenv>=1.0.0
Requires-Dist: tavily-python>=0.7.0
Requires-Dist: mcp>=1.0.0
Requires-Dist: typing>=3.10.0.0
Requires-Dist: pydantic>=2.11.7
